mosaicmpi/__init__.py
mosaicmpi/biomart.py
mosaicmpi/cli.py
mosaicmpi/cnmf.py
mosaicmpi/colors.py
mosaicmpi/config.py
mosaicmpi/dataset.py
mosaicmpi/genesets.py
mosaicmpi/integration.py
mosaicmpi/nancorrmp.py
mosaicmpi/network.py
mosaicmpi/orphan.py
mosaicmpi/plots.py
mosaicmpi/utils.py
mosaicmpi-2.8.6.dist-info/licenses/LICENSE
mosaicmpi-2.8.6.dist-info/METADATA
mosaicmpi-2.8.6.dist-info/WHEEL
mosaicmpi-2.8.6.dist-info/entry_points.txt
mosaicmpi-2.8.6.dist-info/top_level.txt
mosaicmpi-2.8.6.dist-info/RECORD
