Metadata-Version: 2.4
Name: mosaicmpi
Version: 2.8.6
Summary: mosaicMPI: Mosaic Multi-resolution Program Integration
Home-page: https://github.com/MorrissyLab/mosaicMPI
Author: Ted Verhey
Author-email: tbverhey@ucalgary.ca
License: "MIT"
Project-URL: Bug Tracker, https://github.com/MorrissyLab/mosaicMPI/issues
Classifier: Programming Language :: Python :: 3
Classifier: Operating System :: OS Independent
Requires-Python: >=3.9
License-File: LICENSE
Requires-Dist: anndata
Requires-Dist: click
Requires-Dist: distinctipy
Requires-Dist: fastcluster
Requires-Dist: igraph
Requires-Dist: matplotlib
Requires-Dist: networkx
Requires-Dist: numpy
Requires-Dist: pandas
Requires-Dist: pygam
Requires-Dist: pygraphviz
Requires-Dist: pyyaml
Requires-Dist: requests
Requires-Dist: scikit-learn
Requires-Dist: scipy
Requires-Dist: seaborn
Requires-Dist: statsmodels
Requires-Dist: tomli
Requires-Dist: tomli-w
Requires-Dist: tqdm
Requires-Dist: upsetplot
Dynamic: license-file
